curious/__init__.py
curious/exc.py
curious/oauth.py
curious/util.py
curious/commands/__init__.py
curious/commands/conditions.py
curious/commands/context.py
curious/commands/converters.py
curious/commands/decorators.py
curious/commands/exc.py
curious/commands/help.py
curious/commands/manager.py
curious/commands/plugin.py
curious/commands/ratelimit.py
curious/commands/utils.py
curious/core/__init__.py
curious/core/chunker.py
curious/core/client.py
curious/core/event.py
curious/core/gateway.py
curious/core/gateway_old.py
curious/core/httpclient.py
curious/core/state.py
curious/core/_ws_wrapper/__init__.py
curious/core/_ws_wrapper/curio_wrapper.py
curious/core/_ws_wrapper/trio_wrapper.py
curious/dataclasses/__init__.py
curious/dataclasses/appinfo.py
curious/dataclasses/attachment.py
curious/dataclasses/bases.py
curious/dataclasses/channel.py
curious/dataclasses/embed.py
curious/dataclasses/emoji.py
curious/dataclasses/guild.py
curious/dataclasses/invite.py
curious/dataclasses/member.py
curious/dataclasses/message.py
curious/dataclasses/permissions.py
curious/dataclasses/presence.py
curious/dataclasses/reaction.py
curious/dataclasses/role.py
curious/dataclasses/search.py
curious/dataclasses/user.py
curious/dataclasses/voice_state.py
curious/dataclasses/webhook.py
curious/dataclasses/widget.py
curious/ext/paginator/__init__.py
curious/ipc/__init__.py
curious/ipc/client.py
curious/ipc/packet.py
discord_curious-0.7.9.dist-info/DESCRIPTION.rst
discord_curious-0.7.9.dist-info/METADATA
discord_curious-0.7.9.dist-info/RECORD
discord_curious-0.7.9.dist-info/WHEEL
discord_curious-0.7.9.dist-info/metadata.json
discord_curious-0.7.9.dist-info/top_level.txt
