Metadata-Version: 2.0
Name: discord-curious
Version: 0.7.9
Summary: An async library for the Discord API
Home-page: https://github.com/SunDwarf/curious
Author: Laura Dickinson
Author-email: l@veriny.tf
License: LGPLv3
Platform: UNKNOWN
Classifier: Programming Language :: Python :: 3.6
Classifier: Programming Language :: Python :: 3.7
Classifier: Programming Language :: Python :: 3 :: Only
Classifier: Framework :: Trio
Classifier: Development Status :: 4 - Beta
Requires-Python: >=3.6.2
Requires-Dist: lomond (==0.1.13)
Requires-Dist: pylru (==1.0.9)
Requires-Dist: oauthlib (<2.1.0,>=2.0.2)
Requires-Dist: pytz (>=2017.3)
Requires-Dist: asks (<1.4.0,>=1.3.0)
Requires-Dist: multidict (<4.2.0,>=4.1.0)
Requires-Dist: multio (<0.3.0,>=0.2.1)
Requires-Dist: async-generator (~=1.9)
Requires-Dist: typing-inspect (>=0.2.0)
Provides-Extra: docs
Requires-Dist: sphinx-py3doc-enhanced-theme; extra == 'docs'
Requires-Dist: sphinx; extra == 'docs'
Requires-Dist: sphinxcontrib-asyncio; extra == 'docs'
Requires-Dist: sphinx-autodoc-typehints; extra == 'docs'
Provides-Extra: voice
Requires-Dist: opuslib (==1.1.0); extra == 'voice'
Requires-Dist: PyNaCL (==1.0.1); extra == 'voice'
